<?xml version="1.0" encoding="UTF-8" ?>
<!-- Generated by Oracle SOA Modeler version 11.1.1.7.0 at [6/14/14 8:03 PM]. -->
<composite name="InsuranceClaimCase"
           revision="1.1"
           label="2014-06-14_20-03-49_415"
           mode="active"
           state="on"
           xmlns="http://xmlns.oracle.com/sca/1.0"
           xmlns:xs="http://www.w3.org/2001/XMLSchema"
           xmlns:wsp="http://schemas.xmlsoap.org/ws/2004/09/policy"
           xmlns:orawsp="http://schemas.oracle.com/ws/2006/01/policy"
           xmlns:ui="http://xmlns.oracle.com/soa/designer/">
  <import namespace="http://xmlns.oracle.com/CaseService"
          location="oramds:/soa/shared/casemgmt/CaseService.wsdl"
          importType="wsdl"/>
  <import namespace="http://xmlns.oracle.com/bpm/case/caseDecision/InsuranceClaimCaseRules_InsuranceClaimCaseRules"
          location="InsuranceClaimCaseRules_InsuranceClaimCaseRules.wsdl"
          importType="wsdl"/>
  <import namespace="http://xmlns.oracle.com/bpmn/bpmnProcess/FNOL"
          location="FNOL.wsdl" importType="wsdl"/>
  <import namespace="http://xmlns.oracle.com/bpel/workflow/taskService"
          location="oramds:/soa/shared/workflow/TaskServiceInterface.wsdl"
          importType="wsdl"/>
  <import namespace="http://xmlns.oracle.com/bpmn/bpmnProcess/UpdateClaim"
          location="UpdateClaim.wsdl" importType="wsdl"/>
  <import namespace="http://xmlns.oracle.com/bpmn/bpmnProcess/Verification"
          location="Verification.wsdl" importType="wsdl"/>
  <import namespace="http://schemas.oracle.com/events/edl/DispatchServiceProvider"
          location="DispatchServiceProvider.edl" importType="edl"/>
  <import namespace="http://xmlns.oracle.com/bpmn/bpmnProcess/Validation"
          location="Validation.wsdl" importType="wsdl"/>
  <import namespace="http://xmlns.oracle.com/bpmn/bpmnProcess/Payment"
          location="Payment.wsdl" importType="wsdl"/>
  <import namespace="http://xmlns.oracle.com/bpmn/bpmnProcess/CustomerAcceptance"
          location="CustomerAcceptance.wsdl" importType="wsdl"/>
  <import namespace="http://xmlns.oracle.com/bpmn/bpmnProcess/Recovery"
          location="Recovery.wsdl" importType="wsdl"/>
  <import namespace="http://xmlns.oracle.com/bpmn/bpmnProcess/Evaluation"
          location="Evaluation.wsdl" importType="wsdl"/>
  <service name="InsuranceClaimCase.service"
           ui:wsdlLocation="oramds:/soa/shared/casemgmt/CaseService.wsdl">
    <interface.wsdl interface="http://xmlns.oracle.com/CaseService#wsdl.interface(CaseServicePortType)"/>
    <binding.ws port="http://xmlns.oracle.com/CaseService#wsdl.endpoint(InsuranceClaimCase.service/CaseServicePort)"/>
  </service>
  <service name="FNOL.service" ui:wsdlLocation="FNOL.wsdl">
    <interface.wsdl interface="http://xmlns.oracle.com/bpmn/bpmnProcess/FNOL#wsdl.interface(FNOLPortType)"
                    callbackInterface="http://xmlns.oracle.com/bpmn/bpmnProcess/FNOL#wsdl.interface(FNOLPortTypeCallBack)"/>
    <binding.ws port="http://xmlns.oracle.com/bpmn/bpmnProcess/FNOL#wsdl.endpoint(FNOL.service/FNOLPort)"/>
    <callback>
      <binding.ws port="http://xmlns.oracle.com/bpmn/bpmnProcess/FNOL#wsdl.endpoint(FNOL.service/FNOLPortTypeCallBack_pt)"/>
    </callback>
  </service>
  <service name="UpdateClaim.service" ui:wsdlLocation="UpdateClaim.wsdl">
    <interface.wsdl interface="http://xmlns.oracle.com/bpmn/bpmnProcess/UpdateClaim#wsdl.interface(UpdateClaimPortType)"
                    callbackInterface="http://xmlns.oracle.com/bpmn/bpmnProcess/UpdateClaim#wsdl.interface(UpdateClaimPortTypeCallBack)"/>
    <binding.ws port="http://xmlns.oracle.com/bpmn/bpmnProcess/UpdateClaim#wsdl.endpoint(UpdateClaim.service/UpdateClaimPort)"/>
    <callback>
      <binding.ws port="http://xmlns.oracle.com/bpmn/bpmnProcess/UpdateClaim#wsdl.endpoint(UpdateClaim.service/UpdateClaimPortTypeCallBack_pt)"/>
    </callback>
  </service>
  <service name="Validation.service" ui:wsdlLocation="Validation.wsdl">
    <interface.wsdl interface="http://xmlns.oracle.com/bpmn/bpmnProcess/Validation#wsdl.interface(ValidationPortType)"
                    callbackInterface="http://xmlns.oracle.com/bpmn/bpmnProcess/Validation#wsdl.interface(ValidationPortTypeCallBack)"/>
    <binding.ws port="http://xmlns.oracle.com/bpmn/bpmnProcess/Validation#wsdl.endpoint(Validation.service/ValidationPort)"/>
    <callback>
      <binding.ws port="http://xmlns.oracle.com/bpmn/bpmnProcess/Validation#wsdl.endpoint(Validation.service/ValidationPortTypeCallBack_pt)"/>
    </callback>
  </service>
  <service name="Verification.service" ui:wsdlLocation="Verification.wsdl">
    <interface.wsdl interface="http://xmlns.oracle.com/bpmn/bpmnProcess/Verification#wsdl.interface(VerificationPortType)"
                    callbackInterface="http://xmlns.oracle.com/bpmn/bpmnProcess/Verification#wsdl.interface(VerificationPortTypeCallBack)"/>
    <binding.ws port="http://xmlns.oracle.com/bpmn/bpmnProcess/Verification#wsdl.endpoint(Verification.service/VerificationPort)"/>
    <callback>
      <binding.ws port="http://xmlns.oracle.com/bpmn/bpmnProcess/Verification#wsdl.endpoint(Verification.service/VerificationPortTypeCallBack_pt)"/>
    </callback>
  </service>
  <service name="Payment.service" ui:wsdlLocation="Payment.wsdl">
    <interface.wsdl interface="http://xmlns.oracle.com/bpmn/bpmnProcess/Payment#wsdl.interface(PaymentPortType)"
                    callbackInterface="http://xmlns.oracle.com/bpmn/bpmnProcess/Payment#wsdl.interface(PaymentPortTypeCallBack)"/>
    <binding.ws port="http://xmlns.oracle.com/bpmn/bpmnProcess/Payment#wsdl.endpoint(Payment.service/PaymentPort)"/>
    <callback>
      <binding.ws port="http://xmlns.oracle.com/bpmn/bpmnProcess/Payment#wsdl.endpoint(Payment.service/PaymentPortTypeCallBack_pt)"/>
    </callback>
  </service>
  <service name="CustomerAcceptance.service"
           ui:wsdlLocation="CustomerAcceptance.wsdl">
    <interface.wsdl interface="http://xmlns.oracle.com/bpmn/bpmnProcess/CustomerAcceptance#wsdl.interface(CustomerAcceptancePortType)"
                    callbackInterface="http://xmlns.oracle.com/bpmn/bpmnProcess/CustomerAcceptance#wsdl.interface(CustomerAcceptancePortTypeCallBack)"/>
    <binding.ws port="http://xmlns.oracle.com/bpmn/bpmnProcess/CustomerAcceptance#wsdl.endpoint(CustomerAcceptance.service/CustomerAcceptancePort)"/>
    <callback>
      <binding.ws port="http://xmlns.oracle.com/bpmn/bpmnProcess/CustomerAcceptance#wsdl.endpoint(CustomerAcceptance.service/CustomerAcceptancePortTypeCallBack_pt)"/>
    </callback>
  </service>
  <service name="Recovery.service" ui:wsdlLocation="Recovery.wsdl">
    <interface.wsdl interface="http://xmlns.oracle.com/bpmn/bpmnProcess/Recovery#wsdl.interface(RecoveryPortType)"
                    callbackInterface="http://xmlns.oracle.com/bpmn/bpmnProcess/Recovery#wsdl.interface(RecoveryPortTypeCallBack)"/>
    <binding.ws port="http://xmlns.oracle.com/bpmn/bpmnProcess/Recovery#wsdl.endpoint(Recovery.service/RecoveryPort)"/>
    <callback>
      <binding.ws port="http://xmlns.oracle.com/bpmn/bpmnProcess/Recovery#wsdl.endpoint(Recovery.service/RecoveryPortTypeCallBack_pt)"/>
    </callback>
  </service>
  <service name="Evaluation.service" ui:wsdlLocation="Evaluation.wsdl">
    <interface.wsdl interface="http://xmlns.oracle.com/bpmn/bpmnProcess/Evaluation#wsdl.interface(EvaluationPortType)"
                    callbackInterface="http://xmlns.oracle.com/bpmn/bpmnProcess/Evaluation#wsdl.interface(EvaluationPortTypeCallBack)"/>
    <binding.ws port="http://xmlns.oracle.com/bpmn/bpmnProcess/Evaluation#wsdl.endpoint(Evaluation.service/EvaluationPort)"/>
    <callback>
      <binding.ws port="http://xmlns.oracle.com/bpmn/bpmnProcess/Evaluation#wsdl.endpoint(Evaluation.service/EvaluationPortTypeCallBack_pt)"/>
    </callback>
  </service>
  <property name="productVersion" type="xs:string" many="false">11.1.1.7.0</property>
  <component name="InsuranceClaimCase">
    <implementation.casemanagement src="case/InsuranceClaimCase.case"/>
  </component>
  <component name="InsuranceClaimCaseRules">
    <implementation.decision src="InsuranceClaimCaseRules.decs"/>
  </component>
  <component name="FNOL">
    <implementation.bpmn src="processes/FNOL.bpmn"/>
  </component>
  <component name="FNOLTask">
    <implementation.workflow src="FNOLTask.task"/>
  </component>
  <component name="UpdateClaim">
    <implementation.bpmn src="processes/UpdateClaim.bpmn"/>
  </component>
  <component name="UpdateClaimTask">
    <implementation.workflow src="UpdateClaimTask.task"/>
  </component>
  <component name="Verification">
    <implementation.bpmn src="processes/Verification.bpmn"/>
    <business-events>
      <publishes xmlns:pub1="http://schemas.oracle.com/events/edl/DispatchServiceProvider"
                 name="pub1:DispatchServ iceProvider"/>
    </business-events>
  </component>
  <component name="EVerificationTask">
    <implementation.workflow src="EVerificationTask.task"/>
  </component>
  <component name="RVerificationTask">
    <implementation.workflow src="RVerificationTask.task"/>
  </component>
  <component name="Validation">
    <implementation.bpmn src="processes/Validation.bpmn"/>
  </component>
  <component name="ValidateClaimTask">
    <implementation.workflow src="ValidateClaimTask.task"/>
  </component>
  <component name="CustomerAcceptanceTask">
    <implementation.workflow src="CustomerAcceptanceTask.task"/>
  </component>
  <component name="Payment">
    <implementation.bpmn src="processes/Payment.bpmn"/>
  </component>
  <component name="CustomerAcceptance">
    <implementation.bpmn src="processes/CustomerAcceptance.bpmn"/>
    <business-events/>
  </component>
  <component name="Recovery">
    <implementation.bpmn src="processes/Recovery.bpmn"/>
  </component>
  <component name="Evaluation">
    <implementation.bpmn src="processes/Evaluation.bpmn"/>
  </component>
  <wire>
    <source.uri>InsuranceClaimCase.service</source.uri>
    <target.uri>InsuranceClaimCase/InsuranceClaimCase.service</target.uri>
  </wire>
  <wire>
    <source.uri>InsuranceClaimCase/InsuranceClaimCaseRules_InsuranceClaimCaseRules</source.uri>
    <target.uri>InsuranceClaimCaseRules/InsuranceClaimCaseRules_InsuranceClaimCaseRules</target.uri>
  </wire>
  <wire>
    <source.uri>FNOL/HumanTasks.FNOLTask.reference</source.uri>
    <target.uri>FNOLTask/TaskService</target.uri>
  </wire>
  <wire>
    <source.uri>FNOL.service</source.uri>
    <target.uri>FNOL/FNOL.service</target.uri>
  </wire>
  <wire>
    <source.uri>InsuranceClaimCase/FNOL.service.reference</source.uri>
    <target.uri>FNOL/FNOL.service</target.uri>
  </wire>
  <wire>
    <source.uri>UpdateClaim/HumanTasks.UpdateClaimTask.reference</source.uri>
    <target.uri>UpdateClaimTask/TaskService</target.uri>
  </wire>
  <wire>
    <source.uri>UpdateClaim.service</source.uri>
    <target.uri>UpdateClaim/UpdateClaim.service</target.uri>
  </wire>
  <wire>
    <source.uri>InsuranceClaimCase/UpdateClaim.service.reference</source.uri>
    <target.uri>UpdateClaim/UpdateClaim.service</target.uri>
  </wire>
  <wire>
    <source.uri>Verification/HumanTasks.EVerificationTask.reference</source.uri>
    <target.uri>EVerificationTask/TaskService</target.uri>
  </wire>
  <wire>
    <source.uri>Verification/HumanTasks.RVerificationTask.reference</source.uri>
    <target.uri>RVerificationTask/TaskService</target.uri>
  </wire>
  <wire>
    <source.uri>Validation/HumanTasks.ValidateClaimTask.reference</source.uri>
    <target.uri>ValidateClaimTask/TaskService</target.uri>
  </wire>
  <wire>
    <source.uri>Validation.service</source.uri>
    <target.uri>Validation/Validation.service</target.uri>
  </wire>
  <wire>
    <source.uri>InsuranceClaimCase/Validation.service.reference</source.uri>
    <target.uri>Validation/Validation.service</target.uri>
  </wire>
  <wire>
    <source.uri>Verification.service</source.uri>
    <target.uri>Verification/Verification.service</target.uri>
  </wire>
  <wire>
    <source.uri>InsuranceClaimCase/Verification.service.reference</source.uri>
    <target.uri>Verification/Verification.service</target.uri>
  </wire>
  <wire>
    <source.uri>Payment.service</source.uri>
    <target.uri>Payment/Payment.service</target.uri>
  </wire>
  <wire>
    <source.uri>InsuranceClaimCase/Payment.service.reference</source.uri>
    <target.uri>Payment/Payment.service</target.uri>
  </wire>
  <wire>
    <source.uri>CustomerAcceptance/HumanTasks.CustomerAcceptanceTask.reference</source.uri>
    <target.uri>CustomerAcceptanceTask/TaskService</target.uri>
  </wire>
  <wire>
    <source.uri>InsuranceClaimCase/CustomerAcceptance.service.reference</source.uri>
    <target.uri>CustomerAcceptance/CustomerAcceptance.service</target.uri>
  </wire>
  <wire>
    <source.uri>CustomerAcceptance.service</source.uri>
    <target.uri>CustomerAcceptance/CustomerAcceptance.service</target.uri>
  </wire>
  <wire>
    <source.uri>Recovery.service</source.uri>
    <target.uri>Recovery/Recovery.service</target.uri>
  </wire>
  <wire>
    <source.uri>InsuranceClaimCase/Recovery.service.reference</source.uri>
    <target.uri>Recovery/Recovery.service</target.uri>
  </wire>
  <wire>
    <source.uri>Evaluation.service</source.uri>
    <target.uri>Evaluation/Evaluation.service</target.uri>
  </wire>
  <wire>
    <source.uri>InsuranceClaimCase/Evaluation.service.reference</source.uri>
    <target.uri>Evaluation/Evaluation.service</target.uri>
  </wire>
</composite>
